upstox_instrument_query/__init__.py
upstox_instrument_query/cli.py
upstox_instrument_query/constants.py
upstox_instrument_query/database.py
upstox_instrument_query/interactive.py
upstox_instrument_query/logging_config.py
upstox_instrument_query/query.py
upstox_instrument_query/utils.py
upstox_instrument_query/yfinance.py
upstox_instrument_query-0.2.1.dist-info/licenses/LICENSE
upstox_instrument_query-0.2.1.dist-info/METADATA
upstox_instrument_query-0.2.1.dist-info/WHEEL
upstox_instrument_query-0.2.1.dist-info/entry_points.txt
upstox_instrument_query-0.2.1.dist-info/top_level.txt
upstox_instrument_query-0.2.1.dist-info/RECORD
