Metadata-Version: 2.4
Name: upstox-instrument-query
Version: 0.2.1
Summary: Efficiently query large Upstox instruments JSON files using SQLite
Home-page: https://github.com/jinto-ag/upstox_instrument_query
Author: Jinto A G
Author-email: Jinto A G <project.jintoag@gmail.com>
License: MIT
Project-URL: Homepage, https://github.com/jinto-ag/upstox_instrument_query
Project-URL: Bug Tracker, https://github.com/jinto-ag/upstox_instrument_query/issues
Classifier: Programming Language :: Python :: 3
Classifier: Programming Language :: Python :: 3.9
Classifier: Programming Language :: Python :: 3.10
Classifier: Programming Language :: Python :: 3.11
Classifier: Programming Language :: Python :: 3.12
Classifier: Programming Language :: Python :: 3.13
Classifier: License :: OSI Approved :: MIT License
Classifier: Operating System :: OS Independent
Classifier: Topic :: Software Development :: Libraries :: Python Modules
Classifier: Topic :: Office/Business :: Financial :: Investment
Classifier: Intended Audience :: Financial and Insurance Industry
Classifier: Intended Audience :: Developers
Requires-Python: >=3.9
License-File: LICENSE
Requires-Dist: requests==2.32.3
Requires-Dist: yfinance>=0.2.58
Dynamic: author
Dynamic: home-page
Dynamic: license-file
Dynamic: requires-python
